cadmus/__init__.py
cadmus-0.1.7.dist-info/WHEEL
cadmus-0.1.7.dist-info/METADATA
cadmus-0.1.7.dist-info/RECORD
