Metadata-Version: 2.1
Name: cadmus
Version: 0.1.7
Summary: Lightweight commands for printing output
Author: Rhaz Solomon
Author-email: rhaz.solomon@gmail.com
Requires-Python: >=3.7,<4.0
Classifier: Programming Language :: Python :: 3
Classifier: Programming Language :: Python :: 3.7
Classifier: Programming Language :: Python :: 3.8
